tinycircuits_a1454/__init__.py
tinycircuits_a1454/tinycircuits_a1454.py
tinycircuits_a1454-0.0.2.dist-info/LICENSE
tinycircuits_a1454-0.0.2.dist-info/METADATA
tinycircuits_a1454-0.0.2.dist-info/WHEEL
tinycircuits_a1454-0.0.2.dist-info/top_level.txt
tinycircuits_a1454-0.0.2.dist-info/RECORD
