Metadata-Version: 2.1
Name: tinycircuits-a1454
Version: 0.0.2
Summary: Wireling Analog Hall Effect Sensor Python library
Home-page: https://github.com/TinyCircuits/TinyCircuits-Wireling-Hall-Effect-Python-AST1006
Author: TinyCircuits
Author-email: info@tinycircuits.com
License: UNKNOWN
Platform: UNKNOWN
Classifier: Programming Language :: Python :: 3
Classifier: License :: OSI Approved :: GNU General Public License v3 (GPLv3)
Classifier: Operating System :: OS Independent
Requires-Python: >=3.6
